dockerhook/__init__.py
dockerhook/config.py
dockerhook/handler.py
dockerhook/util.py
dockerhub_webhook-0.2.1.dist-info/DESCRIPTION.rst
dockerhub_webhook-0.2.1.dist-info/METADATA
dockerhub_webhook-0.2.1.dist-info/RECORD
dockerhub_webhook-0.2.1.dist-info/WHEEL
dockerhub_webhook-0.2.1.dist-info/metadata.json
dockerhub_webhook-0.2.1.dist-info/top_level.txt
