Metadata-Version: 2.0
Name: dockerhub-webhook
Version: 0.2.1
Summary: Webhook handler for dockerhub autodeployments
Home-page: https://github.com/Praisebetoscience/dockerhub-webhook
Author: PraiseBeToScience
Author-email: pbts.reddit@gmail.com
License: Apache License 2.0
Keywords: dockerhub webhook handler
Platform: UNKNOWN
Classifier: Development Status :: 4 - Beta
Classifier: Environment :: Console
Classifier: Framework :: Flask
Classifier: Intended Audience :: Developers
Classifier: Intended Audience :: System Administrators
Classifier: License :: OSI Approved :: Apache Software License
Classifier: Programming Language :: Python :: 3.4
Classifier: Programming Language :: Python :: 3.5
Classifier: Programming Language :: Python :: 3.3
Classifier: Programming Language :: Python :: 3.6
Classifier: Programming Language :: Python :: 3 :: Only
Classifier: Topic :: Utilities
Requires-Dist: Flask (==0.12)
Requires-Dist: requests (==2.13.0)
